LICENSE
README.md
setup.py
src/wayscript/__init__.py
src/wayscript/context.py
src/wayscript/errors.py
src/wayscript/secret_manager.py
src/wayscript/settings.py
src/wayscript/utils.py
src/wayscript.egg-info/PKG-INFO
src/wayscript.egg-info/SOURCES.txt
src/wayscript.egg-info/dependency_links.txt
src/wayscript.egg-info/not-zip-safe
src/wayscript.egg-info/requires.txt
src/wayscript.egg-info/top_level.txt
src/wayscript/integrations/__init__.py
src/wayscript/integrations/slack.py
src/wayscript/integrations/sql.py
src/wayscript/triggers/__init__.py
src/wayscript/triggers/http_trigger.py