Metadata-Version: 2.1
Name: wayscript
Version: 0.4.0
Summary: Quickly build services, data pipelines, internal tools, and more.
Home-page: https://github.com/wayscript/wayscript-python
Author: Team WayScript
Author-email: founders@wayscript.com
License: MIT
Keywords: wayscript,productivity,software,scripts,cloud,tools,backend,trigger,integration,dev,http,webhook
Classifier: Development Status :: 5 - Production/Stable
Classifier: Intended Audience :: Developers
Classifier: Intended Audience :: End Users/Desktop
Classifier: Intended Audience :: Science/Research
Classifier: Topic :: Software Development :: Libraries :: Python Modules
Classifier: Topic :: Communications
Classifier: Topic :: Database
Classifier: Topic :: Office/Business
Classifier: Topic :: Utilities
Classifier: Programming Language :: Python :: 3
Classifier: Programming Language :: Python :: 3.7
Classifier: Programming Language :: Python :: 3.8
Classifier: Programming Language :: Python :: 3.9
Classifier: Programming Language :: Python :: 3.10
Classifier: Programming Language :: Python :: Implementation :: CPython
Classifier: License :: OSI Approved :: MIT License
Classifier: Operating System :: OS Independent
Classifier: Natural Language :: English
License-File: LICENSE
